myriade/__init__.py
myriade/base.py
myriade/branch.py
myriade/datasets.py
myriade/multiclass/__init__.py
myriade/multiclass/balanced.py
myriade/multiclass/manual.py
myriade/multiclass/optimal.py
myriade/multiclass/random.py
myriade/multiclass/test_manual.py
myriade-0.2.0.dist-info/LICENSE
myriade-0.2.0.dist-info/WHEEL
myriade-0.2.0.dist-info/METADATA
myriade-0.2.0.dist-info/RECORD
