Metadata-Version: 2.1
Name: myriade
Version: 0.2.0
Summary: Hierarchical extreme multiclass and multi-label classification.
License: MIT
Author: Max Halford
Author-email: maxhalford25@gmail.com
Requires-Python: >=3.10,<4.0
Classifier: License :: OSI Approved :: MIT License
Classifier: Programming Language :: Python :: 3
Classifier: Programming Language :: Python :: 3.10
Classifier: Programming Language :: Python :: 3.11
Requires-Dist: scikit-learn (>=1.2.0,<2.0.0)
Requires-Dist: scipy (>=1.9.3,<2.0.0)
